Metadata-Version: 2.4
Name: broinsight
Version: 0.1.8
Summary: If you don't know what to do with your data, I got you, Bro!
Requires-Python: >=3.12
License-File: LICENSE
Requires-Dist: broflow>=0.1.5
Requires-Dist: brollm>=0.1.2
Requires-Dist: broprompt>=0.1.5
Requires-Dist: duckdb>=1.3.2
Requires-Dist: nbformat>=5.10.4
Requires-Dist: pandas>=2.3.2
Requires-Dist: plotly>=6.3.0
Requires-Dist: pydantic>=2.11.7
Requires-Dist: seaborn>=0.13.2
Requires-Dist: importlib-resources>=1.3.0; python_version < "3.9"
Dynamic: license-file
